./.env.example
./.gitignore
./.python-version
./CONTRIBUTING.md
./Dockerfile
./Dockerfile.test
./LICENSE
./NOTICE
./PKG-INFO
./README.md
./README_testing.md
./docker-compose.yml
./poetry.lock
./pyproject.toml
./run_tests.sh
./splunk_mcp.py
./test_config.py
./test_endpoints.py
./uv.lock
./.github/dependabot.yml
./tests/__init__.py
./tests/test_config.py
./tests/test_endpoints_pytest.py
./tests/test_mcp.py
iflow_mcp_splunk_mcp-0.3.0.dist-info/METADATA
iflow_mcp_splunk_mcp-0.3.0.dist-info/WHEEL
iflow_mcp_splunk_mcp-0.3.0.dist-info/entry_points.txt
iflow_mcp_splunk_mcp-0.3.0.dist-info/licenses/LICENSE
iflow_mcp_splunk_mcp-0.3.0.dist-info/licenses/NOTICE
iflow_mcp_splunk_mcp-0.3.0.dist-info/RECORD
