Metadata-Version: 2.4
Name: iflow-mcp_splunk-mcp
Version: 0.3.0
Summary: A FastMCP-based tool for interacting with Splunk Enterprise/Cloud through natural language
License-File: LICENSE
License-File: NOTICE
Requires-Python: >=3.10
Requires-Dist: aiohttp<4.0.0,>=3.11.14
Requires-Dist: fastapi>=0.104.0
Requires-Dist: fastmcp>=0.4.0
Requires-Dist: httpx-sse>=0.4.0
Requires-Dist: httpx>=0.28.0
Requires-Dist: mcp>=1.5.0
Requires-Dist: pydantic-settings>=2.0.0
Requires-Dist: pydantic>=2.0.0
Requires-Dist: python-decouple>=3.8
Requires-Dist: python-dotenv>=1.0.0
Requires-Dist: requests>=2.31.0
Requires-Dist: splunk-sdk>=1.7.4
Requires-Dist: sse-starlette>=1.8.0
Requires-Dist: starlette>=0.27.0
Requires-Dist: typer>=0.9.0
Requires-Dist: uvicorn>=0.23.1
Provides-Extra: dev
Requires-Dist: black>=25.1.0; extra == 'dev'
Requires-Dist: isort>=6.0.0; extra == 'dev'
Requires-Dist: mypy>=1.0.0; extra == 'dev'
Requires-Dist: pytest-asyncio>=0.21.0; extra == 'dev'
Requires-Dist: pytest-cov>=4.1.0; extra == 'dev'
Requires-Dist: pytest-mock>=3.14.1; extra == 'dev'
Requires-Dist: pytest>=8.3.0; extra == 'dev'
